decolog/logger.py
decolog-0.0.6.dist-info/licenses/LICENSE
decolog-0.0.6.dist-info/METADATA
decolog-0.0.6.dist-info/WHEEL
decolog-0.0.6.dist-info/top_level.txt
decolog-0.0.6.dist-info/RECORD
