Metadata-Version: 2.4
Name: decolog
Version: 0.0.6
Summary: A simple logger usable as decorator
Author: Cyril Quijoux
Project-URL: Homepage, https://github.com/crlqjx/decolog/
Keywords: log,decorator
Classifier: Programming Language :: Python :: 3
Requires-Python: >=3.11
License-File: LICENSE
Dynamic: license-file
